yaxp/__init__.py
yaxp/_xpath.py
yaxp-1.0.1.dist-info/METADATA
yaxp-1.0.1.dist-info/WHEEL
yaxp-1.0.1.dist-info/top_level.txt
yaxp-1.0.1.dist-info/RECORD
