Metadata-Version: 2.1
Name: yaxp
Version: 1.0.1
Summary: intuitive xpath generator
Project-URL: Homepage, https://github.com/realtimeprojects/yaxp
Project-URL: Bug Tracker, https://github.com/realtimeprojects/yaxp/issues
Keywords: xpath,selenium,xml
